pygrowup_erknet/__init__.py
pygrowup_erknet/exceptions.py
pygrowup_erknet/pygrowup.py
pygrowup_erknet/tests.py
pygrowup_erknet/tables/__init__.py
pygrowup_erknet/tables/lms.py
pygrowup_erknet/tables/math.py
pygrowup_erknet/tables/sex.py
pygrowup_erknet/tables/table.py
pygrowup_erknet/tables/__pycache__/__init__.cpython-312.pyc
pygrowup_erknet/tables/__pycache__/lms.cpython-312.pyc
pygrowup_erknet/tables/__pycache__/math.cpython-312.pyc
pygrowup_erknet/tables/__pycache__/sex.cpython-312.pyc
pygrowup_erknet/tables/__pycache__/table.cpython-312.pyc
pygrowup_erknet/tables/cdc/__init__.py
pygrowup_erknet/tables/cdc/base.py
pygrowup_erknet/tables/cdc/bmi_for_age.py
pygrowup_erknet/tables/cdc/head_circumference_for_age.py
pygrowup_erknet/tables/cdc/height_for_age.py
pygrowup_erknet/tables/cdc/length_for_age.py
pygrowup_erknet/tables/cdc/weight_for_age.py
pygrowup_erknet/tables/cdc/weight_for_age_infant.py
pygrowup_erknet/tables/cdc/weight_for_height.py
pygrowup_erknet/tables/cdc/weight_for_length.py
pygrowup_erknet/tables/cdc/__pycache__/__init__.cpython-312.pyc
pygrowup_erknet/tables/cdc/__pycache__/base.cpython-312.pyc
pygrowup_erknet/tables/cdc/__pycache__/bmi_for_age.cpython-312.pyc
pygrowup_erknet/tables/cdc/__pycache__/head_circumference_for_age.cpython-312.pyc
pygrowup_erknet/tables/cdc/__pycache__/height_for_age.cpython-312.pyc
pygrowup_erknet/tables/cdc/__pycache__/length_for_age.cpython-312.pyc
pygrowup_erknet/tables/cdc/__pycache__/weight_for_age.cpython-312.pyc
pygrowup_erknet/tables/cdc/__pycache__/weight_for_age_infant.cpython-312.pyc
pygrowup_erknet/tables/cdc/__pycache__/weight_for_height.cpython-312.pyc
pygrowup_erknet/tables/cdc/__pycache__/weight_for_length.cpython-312.pyc
pygrowup_erknet/tables/who/__init__.py
pygrowup_erknet/tables/who/base.py
pygrowup_erknet/tables/who/bmi_for_age_boys.py
pygrowup_erknet/tables/who/bmi_for_age_girls.py
pygrowup_erknet/tables/who/head_circumference_for_age_boys.py
pygrowup_erknet-0.9.4.dist-info/AUTHORS
pygrowup_erknet-0.9.4.dist-info/LICENSE
pygrowup_erknet-0.9.4.dist-info/METADATA
pygrowup_erknet-0.9.4.dist-info/WHEEL
pygrowup_erknet-0.9.4.dist-info/top_level.txt
pygrowup_erknet-0.9.4.dist-info/RECORD
