Metadata-Version: 2.1
Name: pygrowup_erknet
Version: 0.9.4
Summary: Calculate z-scores of anthropometric measurements based on WHO and CDC child growth standards
Home-page: https://github.com/eyal-erknet/pygrowup
Download-URL: https://pypi.org/project/pygrowup-erknet/0.9.4
Author: Evan Wheeler
Author-email: evanmwheeler@gmail.com
Maintainer: Eyal Rahmani
Maintainer-email: eyal.rahmani@med.uni-heidelberg.de
License: BSD
Classifier: Intended Audience :: Healthcare Industry
Classifier: Programming Language :: Python :: 3
Classifier: License :: OSI Approved :: BSD License
Classifier: Topic :: Scientific/Engineering :: Bio-Informatics
Classifier: Operating System :: MacOS :: MacOS X
Classifier: Operating System :: Microsoft :: Windows
Classifier: Operating System :: POSIX
License-File: LICENSE
License-File: AUTHORS
Requires-Dist: openpyxl
Requires-Dist: requests
